qwed_mcp/__init__.py
qwed_mcp/server.py
qwed_mcp/tools.py
qwed_mcp/engines/__init__.py
qwed_mcp/engines/code_engine.py
qwed_mcp/engines/logic_engine.py
qwed_mcp/engines/math_engine.py
qwed_mcp/engines/sql_engine.py
qwed_mcp-0.1.0.dist-info/licenses/LICENSE
qwed_mcp-0.1.0.dist-info/METADATA
qwed_mcp-0.1.0.dist-info/WHEEL
qwed_mcp-0.1.0.dist-info/entry_points.txt
qwed_mcp-0.1.0.dist-info/top_level.txt
qwed_mcp-0.1.0.dist-info/RECORD
