Metadata-Version: 2.4
Name: qwed-mcp
Version: 0.1.0
Summary: MCP Server for QWED Verification - Use QWED verification tools in Claude Desktop, VS Code, and any MCP client
Author-email: Rahul Dass <rahul@qwedai.com>
License:                                  Apache License
Project-URL: Homepage, https://github.com/QWED-AI/qwed-mcp
Project-URL: Documentation, https://docs.qwedai.com
Project-URL: Repository, https://github.com/QWED-AI/qwed-mcp
Keywords: mcp,model-context-protocol,verification,llm,anthropic,claude,qwed
Classifier: Development Status :: 4 - Beta
Classifier: Intended Audience :: Developers
Classifier: License :: OSI Approved :: Apache Software License
Classifier: Programming Language :: Python :: 3
Classifier: Programming Language :: Python :: 3.10
Classifier: Programming Language :: Python :: 3.11
Classifier: Programming Language :: Python :: 3.12
Requires-Python: >=3.10
License-File: LICENSE
Requires-Dist: mcp>=1.2.0
Requires-Dist: sympy>=1.12
Requires-Dist: z3-solver>=4.12.0
Requires-Dist: httpx>=0.24.0
Provides-Extra: dev
Requires-Dist: pytest>=7.0.0; extra == "dev"
Requires-Dist: pytest-asyncio>=0.21.0; extra == "dev"
Requires-Dist: black>=23.0.0; extra == "dev"
Dynamic: license-file
